ref_builder/__init__.py
ref_builder/build.py
ref_builder/cli/__init__.py
ref_builder/cli/main.py
ref_builder/cli/otu.py
ref_builder/cli/validate.py
ref_builder/console.py
ref_builder/events/__init__.py
ref_builder/events/base.py
ref_builder/events/isolate.py
ref_builder/events/otu.py
ref_builder/events/repo.py
ref_builder/events/sequence.py
ref_builder/index.py
ref_builder/legacy/__init__.py
ref_builder/legacy/convert.py
ref_builder/legacy/handlers.py
ref_builder/legacy/models.py
ref_builder/legacy/repo.py
ref_builder/legacy/utils.py
ref_builder/legacy/validate.py
ref_builder/logs.py
ref_builder/models.py
ref_builder/ncbi/__init__.py
ref_builder/ncbi/cache.py
ref_builder/ncbi/client.py
ref_builder/ncbi/models.py
ref_builder/options.py
ref_builder/otu/__init__.py
ref_builder/otu/create.py
ref_builder/otu/isolate.py
ref_builder/otu/models.py
ref_builder/otu/modify.py
ref_builder/otu/update.py
ref_builder/otu/utils.py
ref_builder/paths.py
ref_builder/plan.py
ref_builder/repo.py
ref_builder/resources.py
ref_builder/utils.py
ref_builder-0.28.0.dist-info/METADATA
ref_builder-0.28.0.dist-info/WHEEL
ref_builder-0.28.0.dist-info/entry_points.txt
ref_builder-0.28.0.dist-info/RECORD
